kisti_flydog_text_writer/__init__.py
kisti_flydog_text_writer/server.py
kisti_flydog_text_writer_haryu5412-0.1.0.dist-info/METADATA
kisti_flydog_text_writer_haryu5412-0.1.0.dist-info/WHEEL
kisti_flydog_text_writer_haryu5412-0.1.0.dist-info/entry_points.txt
kisti_flydog_text_writer_haryu5412-0.1.0.dist-info/RECORD
