Metadata-Version: 2.4
Name: kisti-flydog-text-writer-haryu5412
Version: 0.1.0
Summary: Add your description here
Author-email: Haryu5412 <126925788+Haryu5412Dev@users.noreply.github.com>
Requires-Python: >=3.11
Requires-Dist: build>=1.3.0
Requires-Dist: mcp[cil]>=1.24.0
Requires-Dist: twine>=6.2.0
